datafest_archive/__init__.py
datafest_archive/__main__.py
datafest_archive/builder/advisor_page_builder.py
datafest_archive/builder/menu_builder.py
datafest_archive/builder/page_builder.py
datafest_archive/builder/project_page_builder.py
datafest_archive/builder/semester_page_builder.py
datafest_archive/builder/student_page_builder.py
datafest_archive/builder/templating.py
datafest_archive/builder/website_buider.py
datafest_archive/constants.py
datafest_archive/models/database.py
datafest_archive/models/website/configuration.py
datafest_archive/models/website/pages.py
datafest_archive/project_call_subcommand.py
datafest_archive/reader/main.py
datafest_archive/reader/sqlite_reader.py
datafest_archive/reader/sqlite_writer.py
datafest_archive/spreadsheet/__main__.py
datafest_archive/templates/advisor_page.md.jinja
datafest_archive/templates/project_page.md.jinja
datafest_archive/templates/semester_projects.md.jinja
datafest_archive/templates/student_page.md.jinja
datafest_archive/utils.py
datafest_archive/website_subcommand.py
datafest_archive-1.0.0.dist-info/LICENSE
datafest_archive-1.0.0.dist-info/METADATA
datafest_archive-1.0.0.dist-info/WHEEL
datafest_archive-1.0.0.dist-info/entry_points.txt
datafest_archive-1.0.0.dist-info/RECORD
