Metadata-Version: 2.1
Name: datafest-archive
Version: 1.0.0
Summary: DataFestArchive is a Python package designed to generate the DataFestArchive website from past versions of DataFest
Home-page: https://github.com/ckids-datafirst/archive
License: MIT
Author: ckids-datafirst
Author-email: mosorio@isi.edu
Requires-Python: >=3.9,<4.0
Classifier: Development Status :: 3 - Alpha
Classifier: Intended Audience :: Developers
Classifier: License :: OSI Approved :: MIT License
Classifier: Operating System :: OS Independent
Classifier: Programming Language :: Python :: 3
Classifier: Programming Language :: Python :: 3.9
Classifier: Programming Language :: Python :: 3.10
Classifier: Programming Language :: Python :: 3.11
Classifier: Topic :: Software Development :: Libraries :: Python Modules
Requires-Dist: dataclass-wizard (>=0.22.2,<0.23.0)
Requires-Dist: jinja2 (>=3.1.2,<4.0.0)
Requires-Dist: pyyaml (>=6.0.1,<7.0.0)
Requires-Dist: rich (>=13.5.2,<14.0.0)
Requires-Dist: typer[all] (>=0.9.0,<0.10.0)
Project-URL: Repository, https://github.com/ckids-datafirst/archive
